triex/__init__.py
triex/cli.py
triex/py.typed
triex/triex.py
py_triex-2.0.6.dist-info/LICENSE
py_triex-2.0.6.dist-info/METADATA
py_triex-2.0.6.dist-info/WHEEL
py_triex-2.0.6.dist-info/entry_points.txt
py_triex-2.0.6.dist-info/RECORD
