Metadata-Version: 2.1
Name: py-triex
Version: 2.0.6
Summary: A tool to generate semi-minimized regular expression alternations.
Home-page: https://github.com.com/lojoja/triex
License: MIT
Author: lojoja
Author-email: dev@lojoja.com
Requires-Python: >=3.10.0,<4.0.0
Classifier: Development Status :: 5 - Production/Stable
Classifier: License :: OSI Approved :: MIT License
Classifier: Operating System :: OS Independent
Classifier: Programming Language :: Python :: 3
Classifier: Programming Language :: Python :: 3.10
Classifier: Programming Language :: Python :: 3.11
Classifier: Programming Language :: Python :: 3.12
Requires-Dist: click (>=8.0.0,<9.0.0)
Requires-Dist: clickext (>=1.0.1,<2.0.0)
Project-URL: Bug Tracker, https://github.com/lojoja/triex/issues
Project-URL: Repository, https://github.com.com/lojoja/triex
